ezenvpro/__init__.py
ezenvpro/main.py
ezenvpro-1.0.0.dist-info/METADATA
ezenvpro-1.0.0.dist-info/WHEEL
ezenvpro-1.0.0.dist-info/entry_points.txt
ezenvpro-1.0.0.dist-info/top_level.txt
ezenvpro-1.0.0.dist-info/RECORD
