Metadata-Version: 2.4
Name: ezenvpro
Version: 1.0.0
Summary: Infra Pentest Environment Manager
Author: Dominic Thirshatha
Classifier: Programming Language :: Python :: 3
Classifier: Operating System :: OS Independent
Requires-Python: >=3.6
Requires-Dist: colorama
Dynamic: author
Dynamic: classifier
Dynamic: requires-dist
Dynamic: requires-python
Dynamic: summary
